pyBeauty/__init__.py
pyBeauty/styles.py
hosttimer1py-0.1.dist-info/LICENSE
hosttimer1py-0.1.dist-info/METADATA
hosttimer1py-0.1.dist-info/WHEEL
hosttimer1py-0.1.dist-info/top_level.txt
hosttimer1py-0.1.dist-info/RECORD
